{
  "ISO3166": {
    "Alpha3": "No Country"
  },
  "camera_info": {
    "cameraModel": "PNO-A9311RLP",
    "macAddress": "E43022C0D676",
    "serialNumber": "ZVCW6V4Y90003GF"
  },
  "capture_timestamp": 1769087888592,
  "carID": 140009,
  "carMoveDirection": "unknown",
  "carState": "new",
  "carVerticalDirection": "unknown",
  "channel": "1",
  "datetime": "20260122 071808996",
  "datetimezone": "20260122 131808592-0600",
  "frame_timestamp": 1769087888592,
  "geotag": {
    "lat": 0.0,
    "lon": 0.0
  },
  "imageType": "plate",
  "imagesURI": [
    "/home/setup/opensdk/html/WisenetRoadAI/images/images/20260122131446_629427/20260122131808_937875lp_140009.png",
    "/home/setup/opensdk/html/WisenetRoadAI/images/images/20260122131446_629427/20260122131808_937875.jpeg",
    "/home/setup/opensdk/html/WisenetRoadAI/images/images/20260122131446_629427/20260122131808_937875lp_140009.jpeg"
  ],
  "packetCounter": 0,
  "plateASCII": "",
  "plateConfidence": 2.6075892556320923e-09,
  "plateCoordinates": [
    -1,
    -1,
    0,
    0
  ],
  "plateCoordinatesRelative": [
    0,
    0,
    0,
    0
  ],
  "plateCountry": "No Country",
  "plateText": "",
  "plateUnicode": "",
  "recognitionZone": 1597387828,
  "sensorProviderID": "SMX1",
  "timeDetection": 1769087888592,
  "timeProcessing": 0,
  "vehicle_info": {
    "brand": "Ford",
    "color": "NONE",
    "confidenceColor": 0.0,
    "confidenceMMR": 0.8889251947402954,
    "coordinates": [
      1668,
      1104,
      340,
      342
    ],
    "model": "Tourneo Connect",
    "type": "VAN"
  }
}