{
  "ISO3166": {
    "Alpha3": "IRL"
  },
  "camera_info": {
    "cameraModel": "PNO-A9311RLP",
    "macAddress": "E43022C0D676",
    "serialNumber": "ZVCW6V4Y90003GF"
  },
  "capture_timestamp": 1772051311613,
  "carID": 130218,
  "carMoveDirection": "unknown",
  "carState": "lost",
  "carVerticalDirection": "unknown",
  "channel": "1",
  "datetime": "20260225 142835208",
  "datetimezone": "20260225 202830148-0600",
  "frame_timestamp": 1772051311613,
  "geotag": {
    "lat": 0.0,
    "lon": 0.0
  },
  "imageType": "plate",
  "imagesURI": [
    "/home/setup/opensdk/html/WisenetRoadAI/images/images/20260225192659_648818/20260225202830_310867lp_85FA18.png",
    "/home/setup/opensdk/html/WisenetRoadAI/images/images/20260225192659_648818/20260225202830_310867.jpeg",
    "/home/setup/opensdk/html/WisenetRoadAI/images/images/20260225192659_648818/20260225202830_310867lp_85FA18.jpeg"
  ],
  "packetCounter": 0,
  "plateASCII": "85FA1N",
  "plateConfidence": 0.7877604365348816,
  "plateCoordinates": [
    1038,
    234,
    156,
    66
  ],
  "plateCoordinatesRelative": [
    0,
    0,
    156,
    66
  ],
  "plateCountry": "IRL",
  "plateText": "85FA1N",
  "plateUnicode": "85FA1N",
  "recognitionZone": 1,
  "sensorProviderID": "",
  "timeDetection": 1772051311613,
  "timeProcessing": 0,
  "vehicle_info": {
    "brand": "NONE",
    "color": "BLACK",
    "confidenceColor": 0.0,
    "confidenceMMR": 5.339970111846924,
    "coordinates": [
      520,
      0,
      1212,
      660
    ],
    "model": "None",
    "type": "BUS"
  }
}