{
  "ISO3166": {
    "Alpha3": "FRA"
  },
  "camera_info": {
    "cameraModel": "PNO-A9311RLP",
    "macAddress": "E43022C0D676",
    "serialNumber": "ZVCW6V4Y90003GF"
  },
  "capture_timestamp": 1771188625245,
  "carID": 105105,
  "carMoveDirection": "out",
  "carState": "lost",
  "carVerticalDirection": "down",
  "channel": "1",
  "datetime": "20260215 145030170",
  "datetimezone": "20260215 205025120-0600",
  "frame_timestamp": 1771188625245,
  "geotag": {
    "lat": 0.0,
    "lon": 0.0
  },
  "imageType": "plate",
  "imagesURI": [
    "/home/setup/opensdk/html/WisenetRoadAI/images/images/20260215192331_232032/20260215205025_372341lp_TDY762B.png",
    "/home/setup/opensdk/html/WisenetRoadAI/images/images/20260215192331_232032/20260215205025_372341.jpeg",
    "/home/setup/opensdk/html/WisenetRoadAI/images/images/20260215192331_232032/20260215205025_372341lp_TDY762B.jpeg"
  ],
  "packetCounter": 0,
  "plateASCII": "TDY762B",
  "plateConfidence": 0.8560267686843872,
  "plateCoordinates": [
    1116,
    192,
    141,
    72
  ],
  "plateCoordinatesRelative": [
    0,
    0,
    141,
    72
  ],
  "plateCountry": "FRA",
  "plateText": "TDY762B",
  "plateUnicode": "TDY762B",
  "recognitionZone": 1,
  "sensorProviderID": "",
  "timeDetection": 1771188625245,
  "timeProcessing": 0,
  "vehicle_info": {
    "brand": "Mazda",
    "color": "BLACK",
    "confidenceColor": 0.0,
    "confidenceMMR": 3.967327356338501,
    "coordinates": [
      768,
      0,
      808,
      336
    ],
    "model": "CX-3/CX-30/CX-5/CX-50/CX-60/CX-8/CX-9/CX-90",
    "type": "SUV"
  }
}