{
  "ISO3166": {
    "Alpha3": "No Country"
  },
  "camera_info": {
    "cameraModel": "PNO-A9311RLP",
    "macAddress": "E43022C0D676",
    "serialNumber": "ZVCW6V4Y90003GF"
  },
  "capture_timestamp": 1768932228510,
  "carID": 124864,
  "carMoveDirection": "unknown",
  "carState": "new",
  "carVerticalDirection": "unknown",
  "channel": "1",
  "datetime": "20260120 120349253",
  "datetimezone": "20260120 180348510-0600",
  "frame_timestamp": 1768932228510,
  "geotag": {
    "lat": 0.0,
    "lon": 0.0
  },
  "imageType": "plate",
  "imagesURI": [
    "/home/setup/opensdk/html/WisenetRoadAI/images/images/20260120175902_451229/20260120180349_201299lp_124864.png",
    "/home/setup/opensdk/html/WisenetRoadAI/images/images/20260120175902_451229/20260120180349_201299.jpeg",
    "/home/setup/opensdk/html/WisenetRoadAI/images/images/20260120175902_451229/20260120180349_201299lp_124864.jpeg"
  ],
  "packetCounter": 0,
  "plateASCII": "",
  "plateConfidence": 0.0,
  "plateCoordinates": [
    -1,
    -1,
    0,
    0
  ],
  "plateCoordinatesRelative": [
    0,
    0,
    0,
    0
  ],
  "plateCountry": "No Country",
  "plateText": "",
  "plateUnicode": "",
  "recognitionZone": 0,
  "sensorProviderID": "SMX1",
  "timeDetection": 1768932228510,
  "timeProcessing": 0,
  "vehicle_info": {
    "brand": "NONE",
    "color": "GRAY",
    "confidenceColor": 0.0,
    "confidenceMMR": 0.6105490922927856,
    "coordinates": [
      1752,
      0,
      516,
      156
    ],
    "model": "None",
    "type": "PICKUPTRUCK"
  }
}