{
  "ISO3166": {
    "Alpha3": "FRA"
  },
  "camera_info": {
    "cameraModel": "PNO-A9311RLP",
    "macAddress": "E43022C0D676",
    "serialNumber": "ZVCW6V4Y90003GF"
  },
  "capture_timestamp": 1772147828840,
  "carID": 133537,
  "carMoveDirection": "unknown",
  "carState": "lost",
  "carVerticalDirection": "unknown",
  "channel": "1",
  "datetime": "20260226 171713774",
  "datetimezone": "20260226 231708711-0600",
  "frame_timestamp": 1772147828840,
  "geotag": {
    "lat": 0.0,
    "lon": 0.0
  },
  "imageType": "plate",
  "imagesURI": [
    "/home/setup/opensdk/html/WisenetRoadAI/images/images/20260226223511_397248/20260226231708_950425lp_SVL115B.png",
    "/home/setup/opensdk/html/WisenetRoadAI/images/images/20260226223511_397248/20260226231708_950425.jpeg",
    "/home/setup/opensdk/html/WisenetRoadAI/images/images/20260226223511_397248/20260226231708_950425lp_SVL115B.jpeg"
  ],
  "packetCounter": 0,
  "plateASCII": "SVL115B",
  "plateConfidence": 0.8370535969734192,
  "plateCoordinates": [
    1161,
    207,
    144,
    69
  ],
  "plateCoordinatesRelative": [
    0,
    0,
    144,
    69
  ],
  "plateCountry": "FRA",
  "plateText": "SVL115B",
  "plateUnicode": "SVL115B",
  "recognitionZone": 1,
  "sensorProviderID": "",
  "timeDetection": 1772147828840,
  "timeProcessing": 0,
  "vehicle_info": {
    "brand": "Nissan",
    "color": "GRAY",
    "confidenceColor": 0.0,
    "confidenceMMR": 3.8764398097991943,
    "coordinates": [
      840,
      0,
      780,
      356
    ],
    "model": "Versa",
    "type": "CAR"
  }
}