{
  "ISO3166": {
    "Alpha3": "FRA"
  },
  "camera_info": {
    "cameraModel": "PNO-A9311RLP",
    "macAddress": "E43022C0D676",
    "serialNumber": "ZVCW6V4Y90003GF"
  },
  "capture_timestamp": 1771609295292,
  "carID": 117806,
  "carMoveDirection": "out",
  "carState": "lost",
  "carVerticalDirection": "down",
  "channel": "1",
  "datetime": "20260220 114138772",
  "datetimezone": "20260220 174133722-0600",
  "frame_timestamp": 1771609295292,
  "geotag": {
    "lat": 0.0,
    "lon": 0.0
  },
  "imageType": "plate",
  "imagesURI": [
    "/home/setup/opensdk/html/WisenetRoadAI/images/images/20260220173301_686549/20260220174133_987979lp_SCD301C.png",
    "/home/setup/opensdk/html/WisenetRoadAI/images/images/20260220173301_686549/20260220174133_987979.jpeg",
    "/home/setup/opensdk/html/WisenetRoadAI/images/images/20260220173301_686549/20260220174133_987979lp_SCD301C.jpeg"
  ],
  "packetCounter": 0,
  "plateASCII": "SCD301C",
  "plateConfidence": 0.8370535969734192,
  "plateCoordinates": [
    1053,
    144,
    141,
    63
  ],
  "plateCoordinatesRelative": [
    0,
    0,
    141,
    63
  ],
  "plateCountry": "FRA",
  "plateText": "SCD301C",
  "plateUnicode": "SCD301C",
  "recognitionZone": 1,
  "sensorProviderID": "",
  "timeDetection": 1771609295292,
  "timeProcessing": 0,
  "vehicle_info": {
    "brand": "GMC",
    "color": "WHITE",
    "confidenceColor": 0.0,
    "confidenceMMR": 17.02769660949707,
    "coordinates": [
      632,
      0,
      948,
      308
    ],
    "model": "Yukon",
    "type": "SUV"
  }
}