{
  "ISO3166": {
    "Alpha3": "No Country"
  },
  "camera_info": {
    "cameraModel": "PNO-A9311RLP",
    "macAddress": "E43022C0D676",
    "serialNumber": "ZVCW6V4Y90003GF"
  },
  "capture_timestamp": 1769098338082,
  "carID": 72,
  "carMoveDirection": "unknown",
  "carState": "new",
  "carVerticalDirection": "unknown",
  "channel": "1",
  "datetime": "20260122 101218577",
  "datetimezone": "20260122 161218082-0600",
  "frame_timestamp": 1769098338082,
  "geotag": {
    "lat": 0.0,
    "lon": 0.0
  },
  "imageType": "plate",
  "imagesURI": [
    "/home/setup/opensdk/html/WisenetRoadAI/images/images/20260122160458_551853/20260122161218_520944lp_72.png",
    "/home/setup/opensdk/html/WisenetRoadAI/images/images/20260122160458_551853/20260122161218_520944.jpeg",
    "/home/setup/opensdk/html/WisenetRoadAI/images/images/20260122160458_551853/20260122161218_520944lp_72.jpeg"
  ],
  "packetCounter": 0,
  "plateASCII": "",
  "plateConfidence": 0.0,
  "plateCoordinates": [
    -1,
    -1,
    0,
    0
  ],
  "plateCoordinatesRelative": [
    0,
    0,
    0,
    0
  ],
  "plateCountry": "No Country",
  "plateText": "",
  "plateUnicode": "",
  "recognitionZone": 0,
  "sensorProviderID": "SMX1",
  "timeDetection": 1769098338082,
  "timeProcessing": 0,
  "vehicle_info": {
    "brand": "Hyundai",
    "color": "WHITE",
    "confidenceColor": 0.0,
    "confidenceMMR": 0.9436571598052979,
    "coordinates": [
      2884,
      0,
      952,
      738
    ],
    "model": "Avante/Elantra",
    "type": "CAR"
  }
}