{
  "ISO3166": {
    "Alpha3": "NLD"
  },
  "camera_info": {
    "cameraModel": "PNO-A9311RLP",
    "macAddress": "E43022C0D676",
    "serialNumber": "ZVCW6V4Y90003GF"
  },
  "capture_timestamp": 1770688489372,
  "carID": 90797,
  "carMoveDirection": "unknown",
  "carState": "lost",
  "carVerticalDirection": "unknown",
  "channel": "1",
  "datetime": "20260209 195453362",
  "datetimezone": "20260210 015448307-0600",
  "frame_timestamp": 1770688489372,
  "geotag": {
    "lat": 0.0,
    "lon": 0.0
  },
  "imageType": "plate",
  "imagesURI": [
    "/home/setup/opensdk/html/WisenetRoadAI/images/images/20260210014738_919884/20260210015448_553650lp_HRU865D.png",
    "/home/setup/opensdk/html/WisenetRoadAI/images/images/20260210014738_919884/20260210015448_553650.jpeg",
    "/home/setup/opensdk/html/WisenetRoadAI/images/images/20260210014738_919884/20260210015448_553650lp_HRU865D.jpeg"
  ],
  "packetCounter": 0,
  "plateASCII": "HRU865D",
  "plateConfidence": 0.7455357313156128,
  "plateCoordinates": [
    1137,
    135,
    126,
    45
  ],
  "plateCoordinatesRelative": [
    0,
    0,
    126,
    45
  ],
  "plateCountry": "NLD",
  "plateText": "HRU865D",
  "plateUnicode": "HRU865D",
  "recognitionZone": 1,
  "sensorProviderID": "",
  "timeDetection": 1770688489372,
  "timeProcessing": 0,
  "vehicle_info": {
    "brand": "",
    "color": "NONE",
    "confidenceColor": 0.0,
    "confidenceMMR": 0.0,
    "coordinates": [
      788,
      0,
      776,
      386
    ],
    "model": "",
    "type": ""
  }
}