{
  "ISO3166": {
    "Alpha3": "No Country"
  },
  "camera_info": {
    "cameraModel": "PNO-A9311RLP",
    "macAddress": "E43022C0D676",
    "serialNumber": "ZVCW6V4Y90003GF"
  },
  "capture_timestamp": 1768850356691,
  "carID": 115835,
  "carMoveDirection": "unknown",
  "carState": "new",
  "carVerticalDirection": "unknown",
  "channel": "1",
  "datetime": "20260119 131917535",
  "datetimezone": "20260119 191916691-0600",
  "frame_timestamp": 1768850356691,
  "geotag": {
    "lat": 0.0,
    "lon": 0.0
  },
  "imageType": "plate",
  "imagesURI": [
    "/home/setup/opensdk/html/WisenetRoadAI/images/images/20260119191844_730856/20260119191917_490328lp_115835.png",
    "/home/setup/opensdk/html/WisenetRoadAI/images/images/20260119191844_730856/20260119191917_490328.jpeg",
    "/home/setup/opensdk/html/WisenetRoadAI/images/images/20260119191844_730856/20260119191917_490328lp_115835.jpeg"
  ],
  "packetCounter": 0,
  "plateASCII": "",
  "plateConfidence": 0.0,
  "plateCoordinates": [
    -1,
    -1,
    0,
    0
  ],
  "plateCoordinatesRelative": [
    0,
    0,
    0,
    0
  ],
  "plateCountry": "No Country",
  "plateText": "",
  "plateUnicode": "",
  "recognitionZone": 0,
  "sensorProviderID": "SMX1",
  "timeDetection": 1768850356691,
  "timeProcessing": 0,
  "vehicle_info": {
    "brand": "Hyundai",
    "color": "BLACK",
    "confidenceColor": 0.0,
    "confidenceMMR": 0.29978153109550476,
    "coordinates": [
      3604,
      426,
      228,
      552
    ],
    "model": "IONIQ 6",
    "type": "CAR"
  }
}