{
  "ISO3166": {
    "Alpha3": "NLD"
  },
  "camera_info": {
    "cameraModel": "PNO-A9311RLP",
    "macAddress": "E43022C0D676",
    "serialNumber": "ZVCW6V4Y90003GF"
  },
  "capture_timestamp": 1772245467439,
  "carID": 136915,
  "carMoveDirection": "out",
  "carState": "lost",
  "carVerticalDirection": "down",
  "channel": "1",
  "datetime": "20260227 202432320",
  "datetimezone": "20260228 022427267-0600",
  "frame_timestamp": 1772245467439,
  "geotag": {
    "lat": 0.0,
    "lon": 0.0
  },
  "imageType": "plate",
  "imagesURI": [
    "/home/setup/opensdk/html/WisenetRoadAI/images/images/20260228020851_94363/20260228022427_549458lp_XSF242D.png",
    "/home/setup/opensdk/html/WisenetRoadAI/images/images/20260228020851_94363/20260228022427_549458.jpeg",
    "/home/setup/opensdk/html/WisenetRoadAI/images/images/20260228020851_94363/20260228022427_549458lp_XSF242D.jpeg"
  ],
  "packetCounter": 0,
  "plateASCII": "SF202D",
  "plateConfidence": 0.602343738079071,
  "plateCoordinates": [
    1104,
    219,
    147,
    72
  ],
  "plateCoordinatesRelative": [
    0,
    0,
    147,
    72
  ],
  "plateCountry": "NLD",
  "plateText": "SF202D",
  "plateUnicode": "SF202D",
  "recognitionZone": 1,
  "sensorProviderID": "",
  "timeDetection": 1772245467439,
  "timeProcessing": 0,
  "vehicle_info": {
    "brand": "",
    "color": "NONE",
    "confidenceColor": 0.0,
    "confidenceMMR": 0.0,
    "coordinates": [
      708,
      0,
      944,
      356
    ],
    "model": "",
    "type": ""
  }
}