{
  "ISO3166": {
    "Alpha3": "FRA"
  },
  "camera_info": {
    "cameraModel": "PNO-A9311RLP",
    "macAddress": "E43022C0D676",
    "serialNumber": "ZVCW6V4Y90003GF"
  },
  "capture_timestamp": 1770266365990,
  "carID": 79467,
  "carMoveDirection": "out",
  "carState": "lost",
  "carVerticalDirection": "down",
  "channel": "1",
  "datetime": "20260204 223930916",
  "datetimezone": "20260205 043925861-0600",
  "frame_timestamp": 1770266365990,
  "geotag": {
    "lat": 0.0,
    "lon": 0.0
  },
  "imageType": "plate",
  "imagesURI": [
    "/home/setup/opensdk/html/WisenetRoadAI/images/images/20260205034127_987603/20260205043926_121402lp_SSV291A.png",
    "/home/setup/opensdk/html/WisenetRoadAI/images/images/20260205034127_987603/20260205043926_121402.jpeg",
    "/home/setup/opensdk/html/WisenetRoadAI/images/images/20260205034127_987603/20260205043926_121402lp_SSV291A.jpeg"
  ],
  "packetCounter": 0,
  "plateASCII": "SSU291A",
  "plateConfidence": 0.6863839030265808,
  "plateCoordinates": [
    1053,
    123,
    135,
    69
  ],
  "plateCoordinatesRelative": [
    0,
    0,
    135,
    69
  ],
  "plateCountry": "FRA",
  "plateText": "SSU291A",
  "plateUnicode": "SSU291A",
  "recognitionZone": 1,
  "sensorProviderID": "",
  "timeDetection": 1770266365990,
  "timeProcessing": 0,
  "vehicle_info": {
    "brand": "Bentley",
    "color": "BLACK",
    "confidenceColor": 0.0,
    "confidenceMMR": 3.754326343536377,
    "coordinates": [
      648,
      0,
      804,
      266
    ],
    "model": "Continental GT",
    "type": "CAR"
  }
}