{
  "ISO3166": {
    "Alpha3": "NLD"
  },
  "camera_info": {
    "cameraModel": "PNO-A9311RLP",
    "macAddress": "E43022C0D676",
    "serialNumber": "ZVCW6V4Y90003GF"
  },
  "capture_timestamp": 1770519790310,
  "carID": 86865,
  "carMoveDirection": "unknown",
  "carState": "lost",
  "carVerticalDirection": "unknown",
  "channel": "1",
  "datetime": "20260207 210315220",
  "datetimezone": "20260208 030310170-0600",
  "frame_timestamp": 1770519790310,
  "geotag": {
    "lat": 0.0,
    "lon": 0.0
  },
  "imageType": "plate",
  "imagesURI": [
    "/home/setup/opensdk/html/WisenetRoadAI/images/images/20260208021549_994209/20260208030310_380316lp_RZR999.png",
    "/home/setup/opensdk/html/WisenetRoadAI/images/images/20260208021549_994209/20260208030310_380316.jpeg",
    "/home/setup/opensdk/html/WisenetRoadAI/images/images/20260208021549_994209/20260208030310_380316lp_RZR999.jpeg"
  ],
  "packetCounter": 0,
  "plateASCII": "NZNW59",
  "plateConfidence": 0.6315104365348816,
  "plateCoordinates": [
    1221,
    186,
    144,
    78
  ],
  "plateCoordinatesRelative": [
    0,
    0,
    144,
    78
  ],
  "plateCountry": "NLD",
  "plateText": "NZNW59",
  "plateUnicode": "NZNW59",
  "recognitionZone": 1,
  "sensorProviderID": "",
  "timeDetection": 1770519790310,
  "timeProcessing": 0,
  "vehicle_info": {
    "brand": "",
    "color": "NONE",
    "confidenceColor": 0.0,
    "confidenceMMR": 0.0,
    "coordinates": [
      844,
      0,
      888,
      336
    ],
    "model": "",
    "type": ""
  }
}