{
  "ISO3166": {
    "Alpha3": "FRA"
  },
  "camera_info": {
    "cameraModel": "PNO-A9311RLP",
    "macAddress": "E43022C0D676",
    "serialNumber": "ZVCW6V4Y90003GF"
  },
  "capture_timestamp": 1770765409529,
  "carID": 93013,
  "carMoveDirection": "unknown",
  "carState": "lost",
  "carVerticalDirection": "unknown",
  "channel": "1",
  "datetime": "20260210 171651322",
  "datetimezone": "20260210 231646277-0600",
  "frame_timestamp": 1770765409529,
  "geotag": {
    "lat": 0.0,
    "lon": 0.0
  },
  "imageType": "plate",
  "imagesURI": [
    "/home/setup/opensdk/html/WisenetRoadAI/images/images/20260210224353_925999/20260210231646_550322lp_RZV637A.png",
    "/home/setup/opensdk/html/WisenetRoadAI/images/images/20260210224353_925999/20260210231646_550322.jpeg",
    "/home/setup/opensdk/html/WisenetRoadAI/images/images/20260210224353_925999/20260210231646_550322lp_RZV637A.jpeg"
  ],
  "packetCounter": 0,
  "plateASCII": "RZV637A",
  "plateConfidence": 0.875,
  "plateCoordinates": [
    1059,
    102,
    141,
    72
  ],
  "plateCoordinatesRelative": [
    0,
    0,
    141,
    72
  ],
  "plateCountry": "FRA",
  "plateText": "RZV637A",
  "plateUnicode": "RZV637A",
  "recognitionZone": 1,
  "sensorProviderID": "",
  "timeDetection": 1770765409529,
  "timeProcessing": 0,
  "vehicle_info": {
    "brand": "Honda",
    "color": "BLACK",
    "confidenceColor": 0.0,
    "confidenceMMR": 13.338658332824707,
    "coordinates": [
      732,
      0,
      792,
      312
    ],
    "model": "Civic  USA ",
    "type": "CAR"
  }
}