{
  "ISO3166": {
    "Alpha3": "No Country"
  },
  "camera_info": {
    "cameraModel": "PNO-A9311RLP",
    "macAddress": "E43022C0D676",
    "serialNumber": "ZVCW6V4Y90003GF"
  },
  "capture_timestamp": 1768944121263,
  "carID": 127178,
  "carMoveDirection": "unknown",
  "carState": "new",
  "carVerticalDirection": "unknown",
  "channel": "1",
  "datetime": "20260120 152202090",
  "datetimezone": "20260120 212201263-0600",
  "frame_timestamp": 1768944121263,
  "geotag": {
    "lat": 0.0,
    "lon": 0.0
  },
  "imageType": "plate",
  "imagesURI": [
    "/home/setup/opensdk/html/WisenetRoadAI/images/images/20260120211701_311675/20260120212202_31779lp_127178.png",
    "/home/setup/opensdk/html/WisenetRoadAI/images/images/20260120211701_311675/20260120212202_31779.jpeg",
    "/home/setup/opensdk/html/WisenetRoadAI/images/images/20260120211701_311675/20260120212202_31779lp_127178.jpeg"
  ],
  "packetCounter": 0,
  "plateASCII": "",
  "plateConfidence": 6.59781983508312e-33,
  "plateCoordinates": [
    -1,
    -1,
    0,
    0
  ],
  "plateCoordinatesRelative": [
    0,
    0,
    0,
    0
  ],
  "plateCountry": "No Country",
  "plateText": "",
  "plateUnicode": "",
  "recognitionZone": 11,
  "sensorProviderID": "SMX1",
  "timeDetection": 1768944121263,
  "timeProcessing": 0,
  "vehicle_info": {
    "brand": "Lexus",
    "color": "BLACK",
    "confidenceColor": 0.0,
    "confidenceMMR": 0.31913018226623535,
    "coordinates": [
      1792,
      0,
      424,
      150
    ],
    "model": "LX",
    "type": "SUV"
  }
}