{
  "ISO3166": {
    "Alpha3": "No Country"
  },
  "camera_info": {
    "cameraModel": "PNO-A9311RLP",
    "macAddress": "E43022C0D676",
    "serialNumber": "ZVCW6V4Y90003GF"
  },
  "capture_timestamp": 1769026624508,
  "carID": 135194,
  "carMoveDirection": "unknown",
  "carState": "new",
  "carVerticalDirection": "unknown",
  "channel": "1",
  "datetime": "20260121 141705163",
  "datetimezone": "20260121 201704508-0600",
  "frame_timestamp": 1769026624508,
  "geotag": {
    "lat": 0.0,
    "lon": 0.0
  },
  "imageType": "plate",
  "imagesURI": [
    "/home/setup/opensdk/html/WisenetRoadAI/images/images/20260121201132_142166/20260121201705_102368lp_135194.png",
    "/home/setup/opensdk/html/WisenetRoadAI/images/images/20260121201132_142166/20260121201705_102368.jpeg",
    "/home/setup/opensdk/html/WisenetRoadAI/images/images/20260121201132_142166/20260121201705_102368lp_135194.jpeg"
  ],
  "packetCounter": 0,
  "plateASCII": "",
  "plateConfidence": 0.0,
  "plateCoordinates": [
    -1,
    -1,
    0,
    0
  ],
  "plateCoordinatesRelative": [
    0,
    0,
    0,
    0
  ],
  "plateCountry": "No Country",
  "plateText": "",
  "plateUnicode": "",
  "recognitionZone": 0,
  "sensorProviderID": "SMX1",
  "timeDetection": 1769026624508,
  "timeProcessing": 0,
  "vehicle_info": {
    "brand": "Nissan",
    "color": "BLACK",
    "confidenceColor": 0.0,
    "confidenceMMR": 0.4683348536491394,
    "coordinates": [
      1716,
      0,
      576,
      126
    ],
    "model": "Titan/Patrol/Armada",
    "type": "PICKUPTRUCK"
  }
}