{
  "ISO3166": {
    "Alpha3": "FRA"
  },
  "camera_info": {
    "cameraModel": "PNO-A9311RLP",
    "macAddress": "E43022C0D676",
    "serialNumber": "ZVCW6V4Y90003GF"
  },
  "capture_timestamp": 1770928653574,
  "carID": 97864,
  "carMoveDirection": "unknown",
  "carState": "lost",
  "carVerticalDirection": "unknown",
  "channel": "1",
  "datetime": "20260212 143737969",
  "datetimezone": "20260212 203732920-0600",
  "frame_timestamp": 1770928653574,
  "geotag": {
    "lat": 0.0,
    "lon": 0.0
  },
  "imageType": "plate",
  "imagesURI": [
    "/home/setup/opensdk/html/WisenetRoadAI/images/images/20260212194415_835559/20260212203733_171070lp_TCU891B.png",
    "/home/setup/opensdk/html/WisenetRoadAI/images/images/20260212194415_835559/20260212203733_171070.jpeg",
    "/home/setup/opensdk/html/WisenetRoadAI/images/images/20260212194415_835559/20260212203733_171070lp_TCU891B.jpeg"
  ],
  "packetCounter": 0,
  "plateASCII": "TCU891B",
  "plateConfidence": 0.8560267686843872,
  "plateCoordinates": [
    867,
    102,
    135,
    69
  ],
  "plateCoordinatesRelative": [
    0,
    0,
    135,
    69
  ],
  "plateCountry": "FRA",
  "plateText": "TCU891B",
  "plateUnicode": "TCU891B",
  "recognitionZone": 1,
  "sensorProviderID": "",
  "timeDetection": 1770928653574,
  "timeProcessing": 0,
  "vehicle_info": {
    "brand": "Nissan",
    "color": "BLUE",
    "confidenceColor": 0.0,
    "confidenceMMR": 3.97971248626709,
    "coordinates": [
      548,
      0,
      780,
      252
    ],
    "model": "Sentra",
    "type": "CAR"
  }
}