{
  "ISO3166": {
    "Alpha3": "FRA"
  },
  "camera_info": {
    "cameraModel": "PNO-A9311RLP",
    "macAddress": "E43022C0D676",
    "serialNumber": "ZVCW6V4Y90003GF"
  },
  "capture_timestamp": 1770928876428,
  "carID": 97878,
  "carMoveDirection": "out",
  "carState": "lost",
  "carVerticalDirection": "down",
  "channel": "1",
  "datetime": "20260212 144120496",
  "datetimezone": "20260212 204115444-0600",
  "frame_timestamp": 1770928876428,
  "geotag": {
    "lat": 0.0,
    "lon": 0.0
  },
  "imageType": "plate",
  "imagesURI": [
    "/home/setup/opensdk/html/WisenetRoadAI/images/images/20260212194415_835559/20260212204115_677480lp_SVW367A.png",
    "/home/setup/opensdk/html/WisenetRoadAI/images/images/20260212194415_835559/20260212204115_677480.jpeg",
    "/home/setup/opensdk/html/WisenetRoadAI/images/images/20260212194415_835559/20260212204115_677480lp_SVW367A.jpeg"
  ],
  "packetCounter": 0,
  "plateASCII": "SVW367A",
  "plateConfidence": 0.8727678656578064,
  "plateCoordinates": [
    1257,
    150,
    144,
    75
  ],
  "plateCoordinatesRelative": [
    0,
    0,
    144,
    75
  ],
  "plateCountry": "FRA",
  "plateText": "SVW367A",
  "plateUnicode": "SVW367A",
  "recognitionZone": 1,
  "sensorProviderID": "",
  "timeDetection": 1770928876428,
  "timeProcessing": 0,
  "vehicle_info": {
    "brand": "Honda",
    "color": "BLUE",
    "confidenceColor": 0.0,
    "confidenceMMR": 3.0056538581848145,
    "coordinates": [
      896,
      2,
      832,
      382
    ],
    "model": "Civic/Civic Ferio/Civic Type R",
    "type": "CAR"
  }
}