{
  "ISO3166": {
    "Alpha3": "No Country"
  },
  "camera_info": {
    "cameraModel": "PNO-A9311RLP",
    "macAddress": "E43022C0D676",
    "serialNumber": "ZVCW6V4Y90003GF"
  },
  "capture_timestamp": 1768949587720,
  "carID": 128086,
  "carMoveDirection": "unknown",
  "carState": "new",
  "carVerticalDirection": "unknown",
  "channel": "1",
  "datetime": "20260120 165308069",
  "datetimezone": "20260120 225307720-0600",
  "frame_timestamp": 1768949587720,
  "geotag": {
    "lat": 0.0,
    "lon": 0.0
  },
  "imageType": "plate",
  "imagesURI": [
    "/home/setup/opensdk/html/WisenetRoadAI/images/images/20260120224557_800365/20260120225308_15272lp_128086.png",
    "/home/setup/opensdk/html/WisenetRoadAI/images/images/20260120224557_800365/20260120225308_15272.jpeg",
    "/home/setup/opensdk/html/WisenetRoadAI/images/images/20260120224557_800365/20260120225308_15272lp_128086.jpeg"
  ],
  "packetCounter": 0,
  "plateASCII": "",
  "plateConfidence": 0.0,
  "plateCoordinates": [
    -1,
    -1,
    0,
    0
  ],
  "plateCoordinatesRelative": [
    0,
    0,
    0,
    0
  ],
  "plateCountry": "No Country",
  "plateText": "",
  "plateUnicode": "",
  "recognitionZone": 0,
  "sensorProviderID": "SMX1",
  "timeDetection": 1768949587720,
  "timeProcessing": 0,
  "vehicle_info": {
    "brand": "NONE",
    "color": "NONE",
    "confidenceColor": 0.0,
    "confidenceMMR": 0.7500646114349365,
    "coordinates": [
      1632,
      0,
      516,
      114
    ],
    "model": "None",
    "type": "PICKUPTRUCK"
  }
}