{
  "ISO3166": {
    "Alpha3": "USA"
  },
  "camera_info": {
    "cameraModel": "PNO-A9311RLP",
    "macAddress": "E43022C0D676",
    "serialNumber": "ZVCW6V4Y90003GF"
  },
  "capture_timestamp": 1769045515166,
  "carID": 138187,
  "carMoveDirection": "unknown",
  "carState": "new",
  "carVerticalDirection": "unknown",
  "channel": "1",
  "datetime": "20260121 193155835",
  "datetimezone": "20260122 013155166-0600",
  "frame_timestamp": 1769045515166,
  "geotag": {
    "lat": 0.0,
    "lon": 0.0
  },
  "imageType": "plate",
  "imagesURI": [
    "/home/setup/opensdk/html/WisenetRoadAI/images/images/20260122011932_466761/20260122013155_746249lp_RB081.png",
    "/home/setup/opensdk/html/WisenetRoadAI/images/images/20260122011932_466761/20260122013155_746249.jpeg",
    "/home/setup/opensdk/html/WisenetRoadAI/images/images/20260122011932_466761/20260122013155_746249lp_RB081.jpeg"
  ],
  "packetCounter": 0,
  "plateASCII": "RB081",
  "plateConfidence": 0.2823437452316284,
  "plateCoordinates": [
    2258,
    115,
    180,
    57
  ],
  "plateCoordinatesRelative": [
    0,
    0,
    180,
    57
  ],
  "plateCountry": "USA",
  "plateText": "RB081",
  "plateUnicode": "RB081",
  "recognitionZone": 2,
  "sensorProviderID": "SMX1",
  "timeDetection": 1769045515166,
  "timeProcessing": 0,
  "vehicle_info": {
    "brand": "",
    "color": "NONE",
    "confidenceColor": 0.0,
    "confidenceMMR": 0.0,
    "coordinates": [
      1992,
      0,
      544,
      234
    ],
    "model": "",
    "type": ""
  }
}