{
  "ISO3166": {
    "Alpha3": "FRA"
  },
  "camera_info": {
    "cameraModel": "PNO-A9311RLP",
    "macAddress": "E43022C0D676",
    "serialNumber": "ZVCW6V4Y90003GF"
  },
  "capture_timestamp": 1771684865635,
  "carID": 119998,
  "carMoveDirection": "unknown",
  "carState": "lost",
  "carVerticalDirection": "unknown",
  "channel": "1",
  "datetime": "20260221 084109686",
  "datetimezone": "20260221 144104632-0600",
  "frame_timestamp": 1771684865635,
  "geotag": {
    "lat": 0.0,
    "lon": 0.0
  },
  "imageType": "plate",
  "imagesURI": [
    "/home/setup/opensdk/html/WisenetRoadAI/images/images/20260221113728_882501/20260221144104_912833lp_A465MKY.png",
    "/home/setup/opensdk/html/WisenetRoadAI/images/images/20260221113728_882501/20260221144104_912833.jpeg",
    "/home/setup/opensdk/html/WisenetRoadAI/images/images/20260221113728_882501/20260221144104_912833lp_A465MKY.jpeg"
  ],
  "packetCounter": 0,
  "plateASCII": "A465MKY",
  "plateConfidence": 0.8649553656578064,
  "plateCoordinates": [
    918,
    90,
    132,
    69
  ],
  "plateCoordinatesRelative": [
    0,
    0,
    132,
    69
  ],
  "plateCountry": "FRA",
  "plateText": "A465MKY",
  "plateUnicode": "A465MKY",
  "recognitionZone": 1,
  "sensorProviderID": "",
  "timeDetection": 1771684865635,
  "timeProcessing": 0,
  "vehicle_info": {
    "brand": "SEAT",
    "color": "WHITE",
    "confidenceColor": 0.0,
    "confidenceMMR": 9.663769721984863,
    "coordinates": [
      624,
      0,
      712,
      228
    ],
    "model": "Exeo/Ibiza",
    "type": "CAR"
  }
}