{
  "ISO3166": {
    "Alpha3": "No Country"
  },
  "camera_info": {
    "cameraModel": "PNO-A9311RLP",
    "macAddress": "E43022C0D676",
    "serialNumber": "ZVCW6V4Y90003GF"
  },
  "capture_timestamp": 1768857657853,
  "carID": 117250,
  "carMoveDirection": "unknown",
  "carState": "new",
  "carVerticalDirection": "unknown",
  "channel": "1",
  "datetime": "20260119 152058577",
  "datetimezone": "20260119 212057853-0600",
  "frame_timestamp": 1768857657853,
  "geotag": {
    "lat": 0.0,
    "lon": 0.0
  },
  "imageType": "plate",
  "imagesURI": [
    "/home/setup/opensdk/html/WisenetRoadAI/images/images/20260119211850_669118/20260119212058_522505lp_117250.png",
    "/home/setup/opensdk/html/WisenetRoadAI/images/images/20260119211850_669118/20260119212058_522505.jpeg",
    "/home/setup/opensdk/html/WisenetRoadAI/images/images/20260119211850_669118/20260119212058_522505lp_117250.jpeg"
  ],
  "packetCounter": 0,
  "plateASCII": "",
  "plateConfidence": 0.0,
  "plateCoordinates": [
    -1,
    -1,
    0,
    0
  ],
  "plateCoordinatesRelative": [
    0,
    0,
    0,
    0
  ],
  "plateCountry": "No Country",
  "plateText": "",
  "plateUnicode": "",
  "recognitionZone": 0,
  "sensorProviderID": "SMX1",
  "timeDetection": 1768857657853,
  "timeProcessing": 0,
  "vehicle_info": {
    "brand": "Peterbilt",
    "color": "BLACK",
    "confidenceColor": 0.0,
    "confidenceMMR": 0.5610306262969971,
    "coordinates": [
      1836,
      0,
      516,
      102
    ],
    "model": "365/367/389",
    "type": "TRUCK"
  }
}