{
  "ISO3166": {
    "Alpha3": "FRA"
  },
  "camera_info": {
    "cameraModel": "PNO-A9311RLP",
    "macAddress": "E43022C0D676",
    "serialNumber": "ZVCW6V4Y90003GF"
  },
  "capture_timestamp": 1771700076871,
  "carID": 120570,
  "carMoveDirection": "unknown",
  "carState": "lost",
  "carVerticalDirection": "unknown",
  "channel": "1",
  "datetime": "20260221 125441423",
  "datetimezone": "20260221 185436375-0600",
  "frame_timestamp": 1771700076871,
  "geotag": {
    "lat": 0.0,
    "lon": 0.0
  },
  "imageType": "plate",
  "imagesURI": [
    "/home/setup/opensdk/html/WisenetRoadAI/images/images/20260221184934_699130/20260221185436_634282lp_RXL015A.png",
    "/home/setup/opensdk/html/WisenetRoadAI/images/images/20260221184934_699130/20260221185436_634282.jpeg",
    "/home/setup/opensdk/html/WisenetRoadAI/images/images/20260221184934_699130/20260221185436_634282lp_RXL015A.jpeg"
  ],
  "packetCounter": 0,
  "plateASCII": "RXL015A",
  "plateConfidence": 0.8627232313156128,
  "plateCoordinates": [
    897,
    93,
    135,
    72
  ],
  "plateCoordinatesRelative": [
    0,
    0,
    135,
    72
  ],
  "plateCountry": "FRA",
  "plateText": "RXL015A",
  "plateUnicode": "RXL015A",
  "recognitionZone": 1,
  "sensorProviderID": "",
  "timeDetection": 1771700076871,
  "timeProcessing": 0,
  "vehicle_info": {
    "brand": "Honda",
    "color": "RED",
    "confidenceColor": 0.0,
    "confidenceMMR": 1.964529275894165,
    "coordinates": [
      556,
      0,
      808,
      258
    ],
    "model": "CR-V",
    "type": "SUV"
  }
}