{
  "ISO3166": {
    "Alpha3": "USA"
  },
  "camera_info": {
    "cameraModel": "PNO-A9311RLP",
    "macAddress": "E43022C0D676",
    "serialNumber": "ZVCW6V4Y90003GF"
  },
  "capture_timestamp": 1768785010889,
  "carID": 109788,
  "carMoveDirection": "unknown",
  "carState": "new",
  "carVerticalDirection": "unknown",
  "channel": "1",
  "datetime": "20260118 191011577",
  "datetimezone": "20260119 011010889-0600",
  "frame_timestamp": 1768785010889,
  "geotag": {
    "lat": 0.0,
    "lon": 0.0
  },
  "imageType": "plate",
  "imagesURI": [
    "/home/setup/opensdk/html/WisenetRoadAI/images/images/20260119010118_226821/20260119011011_509759lp_RTC504C.png",
    "/home/setup/opensdk/html/WisenetRoadAI/images/images/20260119010118_226821/20260119011011_509759.jpeg",
    "/home/setup/opensdk/html/WisenetRoadAI/images/images/20260119010118_226821/20260119011011_509759lp_RTC504C.jpeg"
  ],
  "packetCounter": 0,
  "plateASCII": "RTC504C",
  "plateConfidence": 0.7176339030265808,
  "plateCoordinates": [
    2001,
    49,
    120,
    51
  ],
  "plateCoordinatesRelative": [
    0,
    0,
    120,
    51
  ],
  "plateCountry": "USA",
  "plateText": "RTC504C",
  "plateUnicode": "RTC504C",
  "recognitionZone": 1,
  "sensorProviderID": "SMX1",
  "timeDetection": 1768785010889,
  "timeProcessing": 0,
  "vehicle_info": {
    "brand": "",
    "color": "NONE",
    "confidenceColor": 0.0,
    "confidenceMMR": 0.0,
    "coordinates": [
      1800,
      0,
      544,
      138
    ],
    "model": "",
    "type": ""
  }
}