{
  "ISO3166": {
    "Alpha3": "FRA"
  },
  "camera_info": {
    "cameraModel": "PNO-A9311RLP",
    "macAddress": "E43022C0D676",
    "serialNumber": "ZVCW6V4Y90003GF"
  },
  "capture_timestamp": 1770305709602,
  "carID": 80115,
  "carMoveDirection": "out",
  "carState": "lost",
  "carVerticalDirection": "down",
  "channel": "1",
  "datetime": "20260205 093514496",
  "datetimezone": "20260205 153509444-0600",
  "frame_timestamp": 1770305709602,
  "geotag": {
    "lat": 0.0,
    "lon": 0.0
  },
  "imageType": "plate",
  "imagesURI": [
    "/home/setup/opensdk/html/WisenetRoadAI/images/images/20260205152759_296608/20260205153509_656671lp_SDP112A.png",
    "/home/setup/opensdk/html/WisenetRoadAI/images/images/20260205152759_296608/20260205153509_656671.jpeg",
    "/home/setup/opensdk/html/WisenetRoadAI/images/images/20260205152759_296608/20260205153509_656671lp_SDP112A.jpeg"
  ],
  "packetCounter": 0,
  "plateASCII": "SDP112A",
  "plateConfidence": 0.8504464030265808,
  "plateCoordinates": [
    1098,
    156,
    138,
    69
  ],
  "plateCoordinatesRelative": [
    0,
    0,
    138,
    69
  ],
  "plateCountry": "FRA",
  "plateText": "SDP112A",
  "plateUnicode": "SDP112A",
  "recognitionZone": 1,
  "sensorProviderID": "",
  "timeDetection": 1770305709602,
  "timeProcessing": 0,
  "vehicle_info": {
    "brand": "KIA",
    "color": "WHITE",
    "confidenceColor": 0.0,
    "confidenceMMR": 1.9999996423721313,
    "coordinates": [
      744,
      0,
      816,
      342
    ],
    "model": "Soul",
    "type": "CAR"
  }
}