{
  "ISO3166": {
    "Alpha3": "FRA"
  },
  "camera_info": {
    "cameraModel": "PNO-A9311RLP",
    "macAddress": "E43022C0D676",
    "serialNumber": "ZVCW6V4Y90003GF"
  },
  "capture_timestamp": 1771462838560,
  "carID": 113447,
  "carMoveDirection": "unknown",
  "carState": "lost",
  "carVerticalDirection": "unknown",
  "channel": "1",
  "datetime": "20260218 190042443",
  "datetimezone": "20260219 010037394-0600",
  "frame_timestamp": 1771462838560,
  "geotag": {
    "lat": 0.0,
    "lon": 0.0
  },
  "imageType": "plate",
  "imagesURI": [
    "/home/setup/opensdk/html/WisenetRoadAI/images/images/20260219003740_386840/20260219010037_669944lp_A117MLD.png",
    "/home/setup/opensdk/html/WisenetRoadAI/images/images/20260219003740_386840/20260219010037_669944.jpeg",
    "/home/setup/opensdk/html/WisenetRoadAI/images/images/20260219003740_386840/20260219010037_669944lp_A117MLD.jpeg"
  ],
  "packetCounter": 0,
  "plateASCII": "A117MLD",
  "plateConfidence": 0.7332589030265808,
  "plateCoordinates": [
    957,
    144,
    129,
    60
  ],
  "plateCoordinatesRelative": [
    0,
    0,
    129,
    60
  ],
  "plateCountry": "FRA",
  "plateText": "A117MLD",
  "plateUnicode": "A117MLD",
  "recognitionZone": 1,
  "sensorProviderID": "",
  "timeDetection": 1771462838560,
  "timeProcessing": 0,
  "vehicle_info": {
    "brand": "Nissan",
    "color": "BLACK",
    "confidenceColor": 0.0,
    "confidenceMMR": 3.658336639404297,
    "coordinates": [
      656,
      0,
      736,
      302
    ],
    "model": "Versa",
    "type": "CAR"
  }
}