{
  "ISO3166": {
    "Alpha3": "ITA"
  },
  "camera_info": {
    "cameraModel": "PNO-A9311RLP",
    "macAddress": "E43022C0D676",
    "serialNumber": "ZVCW6V4Y90003GF"
  },
  "capture_timestamp": 1772067736330,
  "carID": 130973,
  "carMoveDirection": "unknown",
  "carState": "lost",
  "carVerticalDirection": "unknown",
  "channel": "1",
  "datetime": "20260225 190221060",
  "datetimezone": "20260226 010216003-0600",
  "frame_timestamp": 1772067736330,
  "geotag": {
    "lat": 0.0,
    "lon": 0.0
  },
  "imageType": "plate",
  "imagesURI": [
    "/home/setup/opensdk/html/WisenetRoadAI/images/images/20260226005329_507023/20260226010216_202335lp_PZ4412D.png",
    "/home/setup/opensdk/html/WisenetRoadAI/images/images/20260226005329_507023/20260226010216_202335.jpeg",
    "/home/setup/opensdk/html/WisenetRoadAI/images/images/20260226005329_507023/20260226010216_202335lp_PZ4412D.jpeg"
  ],
  "packetCounter": 0,
  "plateASCII": "PZ4412D",
  "plateConfidence": 0.6529017686843872,
  "plateCoordinates": [
    999,
    156,
    141,
    72
  ],
  "plateCoordinatesRelative": [
    0,
    0,
    141,
    72
  ],
  "plateCountry": "ITA",
  "plateText": "PZ4412D",
  "plateUnicode": "PZ4412D",
  "recognitionZone": 1,
  "sensorProviderID": "",
  "timeDetection": 1772067736330,
  "timeProcessing": 0,
  "vehicle_info": {
    "brand": "",
    "color": "NONE",
    "confidenceColor": 0.0,
    "confidenceMMR": 0.0,
    "coordinates": [
      620,
      0,
      912,
      356
    ],
    "model": "",
    "type": ""
  }
}