{
  "ISO3166": {
    "Alpha3": "ITA"
  },
  "camera_info": {
    "cameraModel": "PNO-A9311RLP",
    "macAddress": "E43022C0D676",
    "serialNumber": "ZVCW6V4Y90003GF"
  },
  "capture_timestamp": 1770213481709,
  "carID": 77352,
  "carMoveDirection": "out",
  "carState": "lost",
  "carVerticalDirection": "down",
  "channel": "1",
  "datetime": "20260204 075806443",
  "datetimezone": "20260204 135801398-0600",
  "frame_timestamp": 1770213481709,
  "geotag": {
    "lat": 0.0,
    "lon": 0.0
  },
  "imageType": "plate",
  "imagesURI": [
    "/home/setup/opensdk/html/WisenetRoadAI/images/images/20260204133428_331058/20260204135801_655150lp_RKE464C.png",
    "/home/setup/opensdk/html/WisenetRoadAI/images/images/20260204133428_331058/20260204135801_655150.jpeg",
    "/home/setup/opensdk/html/WisenetRoadAI/images/images/20260204133428_331058/20260204135801_655150lp_RKE464C.jpeg"
  ],
  "packetCounter": 0,
  "plateASCII": "NKE464C",
  "plateConfidence": 0.7745535969734192,
  "plateCoordinates": [
    1422,
    360,
    150,
    81
  ],
  "plateCoordinatesRelative": [
    0,
    0,
    150,
    81
  ],
  "plateCountry": "ITA",
  "plateText": "NKE464C",
  "plateUnicode": "NKE464C",
  "recognitionZone": 1,
  "sensorProviderID": "",
  "timeDetection": 1770213481709,
  "timeProcessing": 0,
  "vehicle_info": {
    "brand": "Dodge",
    "color": "RED",
    "confidenceColor": 0.0,
    "confidenceMMR": 3.301316261291504,
    "coordinates": [
      992,
      0,
      884,
      488
    ],
    "model": "Caravan",
    "type": "VAN"
  }
}