{
  "ISO3166": {
    "Alpha3": "MLT"
  },
  "camera_info": {
    "cameraModel": "PNO-A9311RLP",
    "macAddress": "E43022C0D676",
    "serialNumber": "ZVCW6V4Y90003GF"
  },
  "capture_timestamp": 1771304410742,
  "carID": 108471,
  "carMoveDirection": "unknown",
  "carState": "lost",
  "carVerticalDirection": "unknown",
  "channel": "1",
  "datetime": "20260216 230014930",
  "datetimezone": "20260217 050009872-0600",
  "frame_timestamp": 1771304410742,
  "geotag": {
    "lat": 0.0,
    "lon": 0.0
  },
  "imageType": "plate",
  "imagesURI": [
    "/home/setup/opensdk/html/WisenetRoadAI/images/images/20260217035007_857913/20260217050010_117112lp_HZK657C.png",
    "/home/setup/opensdk/html/WisenetRoadAI/images/images/20260217035007_857913/20260217050010_117112.jpeg",
    "/home/setup/opensdk/html/WisenetRoadAI/images/images/20260217035007_857913/20260217050010_117112lp_HZK657C.jpeg"
  ],
  "packetCounter": 0,
  "plateASCII": "HWKA971",
  "plateConfidence": 0.4453125,
  "plateCoordinates": [
    951,
    222,
    144,
    84
  ],
  "plateCoordinatesRelative": [
    0,
    0,
    144,
    84
  ],
  "plateCountry": "MLT",
  "plateText": "HWKA971",
  "plateUnicode": "HWKA971",
  "recognitionZone": 1,
  "sensorProviderID": "",
  "timeDetection": 1771304410742,
  "timeProcessing": 0,
  "vehicle_info": {
    "brand": "",
    "color": "NONE",
    "confidenceColor": 0.0,
    "confidenceMMR": 0.0,
    "coordinates": [
      632,
      0,
      792,
      434
    ],
    "model": "",
    "type": ""
  }
}