{
  "ISO3166": {
    "Alpha3": "FRA"
  },
  "camera_info": {
    "cameraModel": "PNO-A9311RLP",
    "macAddress": "E43022C0D676",
    "serialNumber": "ZVCW6V4Y90003GF"
  },
  "capture_timestamp": 1771812849455,
  "carID": 123270,
  "carMoveDirection": "unknown",
  "carState": "lost",
  "carVerticalDirection": "unknown",
  "channel": "1",
  "datetime": "20260222 201414343",
  "datetimezone": "20260223 021409292-0600",
  "frame_timestamp": 1771812849455,
  "geotag": {
    "lat": 0.0,
    "lon": 0.0
  },
  "imageType": "plate",
  "imagesURI": [
    "/home/setup/opensdk/html/WisenetRoadAI/images/images/20260223013851_158421/20260223021409_536038lp_SFU374A.png",
    "/home/setup/opensdk/html/WisenetRoadAI/images/images/20260223013851_158421/20260223021409_536038.jpeg",
    "/home/setup/opensdk/html/WisenetRoadAI/images/images/20260223013851_158421/20260223021409_536038lp_SFU374A.jpeg"
  ],
  "packetCounter": 0,
  "plateASCII": "SFU374A",
  "plateConfidence": 0.7879464030265808,
  "plateCoordinates": [
    1287,
    159,
    135,
    69
  ],
  "plateCoordinatesRelative": [
    0,
    0,
    135,
    69
  ],
  "plateCountry": "FRA",
  "plateText": "SFU374A",
  "plateUnicode": "SFU374A",
  "recognitionZone": 1,
  "sensorProviderID": "",
  "timeDetection": 1771812849455,
  "timeProcessing": 0,
  "vehicle_info": {
    "brand": "",
    "color": "NONE",
    "confidenceColor": 0.0,
    "confidenceMMR": 0.0,
    "coordinates": [
      1084,
      0,
      768,
      392
    ],
    "model": "",
    "type": ""
  }
}