{
  "ISO3166": {
    "Alpha3": "No Country"
  },
  "camera_info": {
    "cameraModel": "PNO-A9311RLP",
    "macAddress": "E43022C0D676",
    "serialNumber": "ZVCW6V4Y90003GF"
  },
  "capture_timestamp": 1768925863132,
  "carID": 123955,
  "carMoveDirection": "unknown",
  "carState": "new",
  "carVerticalDirection": "unknown",
  "channel": "1",
  "datetime": "20260120 101744019",
  "datetimezone": "20260120 161743132-0600",
  "frame_timestamp": 1768925863132,
  "geotag": {
    "lat": 0.0,
    "lon": 0.0
  },
  "imageType": "plate",
  "imagesURI": [
    "/home/setup/opensdk/html/WisenetRoadAI/images/images/20260120161506_756394/20260120161743_971099lp_123955.png",
    "/home/setup/opensdk/html/WisenetRoadAI/images/images/20260120161506_756394/20260120161743_971099.jpeg",
    "/home/setup/opensdk/html/WisenetRoadAI/images/images/20260120161506_756394/20260120161743_971099lp_123955.jpeg"
  ],
  "packetCounter": 0,
  "plateASCII": "",
  "plateConfidence": 6.59781983508312e-33,
  "plateCoordinates": [
    -1,
    -1,
    0,
    0
  ],
  "plateCoordinatesRelative": [
    0,
    0,
    0,
    0
  ],
  "plateCountry": "No Country",
  "plateText": "",
  "plateUnicode": "",
  "recognitionZone": 11,
  "sensorProviderID": "SMX1",
  "timeDetection": 1768925863132,
  "timeProcessing": 0,
  "vehicle_info": {
    "brand": "Porsche",
    "color": "WHITE",
    "confidenceColor": 0.0,
    "confidenceMMR": 0.5055356025695801,
    "coordinates": [
      1752,
      0,
      496,
      138
    ],
    "model": "911 GT3/911 GT6/911 R",
    "type": "CAR"
  }
}